po3way.py
po3way-0.1.dist-info/METADATA
po3way-0.1.dist-info/WHEEL
po3way-0.1.dist-info/entry_points.txt
po3way-0.1.dist-info/top_level.txt
po3way-0.1.dist-info/RECORD
